PyDelFEM2/__init__.py
PyDelFEM2/c_core.cpython-37m-darwin.so
PyDelFEM2/c_core.so
PyDelFEM2/cadmsh.py
PyDelFEM2/cadmshsimvis.py
PyDelFEM2/fem.py
PyDelFEM2/util.py
PyDelFEM2/gl/__init__.py
PyDelFEM2/gl/_gl.py
PyDelFEM2/gl/c_gl.cpython-37m-darwin.so
PyDelFEM2/gl/c_gl.so
PyDelFEM2/gl/glfw.py
PyDelFEM2/gl/glut.py
PyDelFEM2/qt/__init__.py
PyDelFEM2/qt/pyqt.py
PyDelFEM2-0.0.11.dist-info/LICENSE
PyDelFEM2-0.0.11.dist-info/METADATA
PyDelFEM2-0.0.11.dist-info/WHEEL
PyDelFEM2-0.0.11.dist-info/top_level.txt
PyDelFEM2-0.0.11.dist-info/RECORD
